{
	"$schema": "http://schema.management.azure.com/schemas/2015-01-01/deploymentTemplate.json#",
	"contentVersion": "1.0.0.0",
	"parameters": {
		"factoryName": {
			"type": "string",
			"metadata": "Data Factory name",
			"defaultValue": "mydatafac567"
		},
		"incrementalStorageTrigger_properties_incrementalDataLoadDifferentFiles_parameters_pfolder": {
			"type": "string",
			"defaultValue": "@triggerBody().folderPath"
		},
		"incrementalStorageTrigger_properties_incrementalDataLoadDifferentFiles_parameters_pfile": {
			"type": "string",
			"defaultValue": "@triggerBody().fileName"
		},
		"incrementalStorageTrigger_properties_incrementalDataLoadDifferentFiles_parameters_puploadedTime": {
			"type": "string",
			"defaultValue": "@triggerBody().eventTime"
		},
		"incrementalStorageTrigger_properties_typeProperties_scope": {
			"type": "string",
			"defaultValue": "/subscriptions/4d829107-c197-4465-8b1b-676ebd2084d8/resourceGroups/abc/providers/Microsoft.Storage/storageAccounts/strgacc670"
		},
		"NewFileArrivalTrigger_properties_PL_MappingDataFlow_parameters_FileName1": {
			"type": "string",
			"defaultValue": "@triggerBody().fileName"
		},
		"NewFileArrivalTrigger_properties_PL_MappingDataFlow_parameters_folderpath": {
			"type": "string",
			"defaultValue": "@join(skip(split(trigger().outputs.folderPath, '/'), 1), '/')"
		},
		"NewFileArrivalTrigger_properties_typeProperties_scope": {
			"type": "string",
			"defaultValue": "/subscriptions/4d829107-c197-4465-8b1b-676ebd2084d8/resourceGroups/abc/providers/Microsoft.Storage/storageAccounts/strgacc670"
		}
	},
	"variables": {
		"factoryId": "[concat('Microsoft.DataFactory/factories/', parameters('factoryName'))]"
	},
	"resources": [
		{
			"name": "[concat(parameters('factoryName'), '/mapping_dataflow')]",
			"type": "Microsoft.DataFactory/factories/dataflows",
			"apiVersion": "2018-06-01",
			"properties": {
				"type": "MappingDataFlow",
				"typeProperties": {
					"sources": [
						{
							"dataset": {
								"referenceName": "bankData",
								"type": "DatasetReference"
							},
							"name": "source1"
						}
					],
					"sinks": [
						{
							"dataset": {
								"referenceName": "DelimitedText4",
								"type": "DatasetReference"
							},
							"name": "sink1"
						},
						{
							"dataset": {
								"referenceName": "Json1",
								"type": "DatasetReference"
							},
							"name": "sink2"
						}
					],
					"transformations": [
						{
							"name": "select1"
						},
						{
							"name": "derivedColumn1"
						},
						{
							"name": "split1"
						}
					],
					"scriptLines": [
						"source(output(",
						"          customer_name as string,",
						"          dob as string,",
						"          pan_number as string,",
						"          aadhaar_number as string,",
						"          mobile as string,",
						"          gender as string,",
						"          address as string,",
						"          pincode as string,",
						"          branch_id as string,",
						"          updated_at as string",
						"     ),",
						"     allowSchemaDrift: true,",
						"     validateSchema: false,",
						"     ignoreNoFilesFound: false) ~> source1",
						"source1 select(mapColumn(",
						"          customerName = customer_name,",
						"          dob,",
						"          panNumber = pan_number,",
						"          aadhaarNumber = aadhaar_number,",
						"          mobile,",
						"          gender,",
						"          address,",
						"          pincode,",
						"          branchId = branch_id,",
						"          updatedAt = updated_at",
						"     ),",
						"     skipDuplicateMapInputs: true,",
						"     skipDuplicateMapOutputs: true) ~> select1",
						"select1 derive(panNumber = iif(isNull(panNumber), 'Na', panNumber),",
						"          aadhaarNumber = iif(isNull(aadhaarNumber),\"00000\",aadhaarNumber),",
						"          gender = iif(isNull(gender), \"Na\", gender),",
						"          Age = currentDate()-toDate(dob),",
						"          panStatus = iif(length(panNumber)==10, \"valid\", \"InValid\"),",
						"          aadharStatus = iif(length(aadhaarNumber)==12, \"Valid\", \"InValid\"),",
						"          column1 = iif(isNull(branchId) || branchId == '', 'INVALID_BRANCH', 'VALID_BRANCH')) ~> derivedColumn1",
						"derivedColumn1 split(panStatus=='Valid'&&aadharStatus=='Valid',",
						"     disjoint: false) ~> split1@(yes, no)",
						"split1@yes sink(allowSchemaDrift: true,",
						"     validateSchema: false,",
						"     umask: 0022,",
						"     preCommands: [],",
						"     postCommands: [],",
						"     skipDuplicateMapInputs: true,",
						"     skipDuplicateMapOutputs: true) ~> sink1",
						"split1@no sink(allowSchemaDrift: true,",
						"     validateSchema: false,",
						"     umask: 0022,",
						"     preCommands: [],",
						"     postCommands: [],",
						"     skipDuplicateMapInputs: true,",
						"     skipDuplicateMapOutputs: true,",
						"     saveOrder: 1) ~> sink2"
					]
				}
			},
			"dependsOn": []
		},
		{
			"name": "[concat(parameters('factoryName'), '/PL_MappingDataFlow')]",
			"type": "Microsoft.DataFactory/factories/pipelines",
			"apiVersion": "2018-06-01",
			"properties": {
				"activities": [
					{
						"name": "Data flow1",
						"type": "ExecuteDataFlow",
						"dependsOn": [],
						"policy": {
							"timeout": "0.12:00:00",
							"retry": 0,
							"retryIntervalInSeconds": 30,
							"secureOutput": false,
							"secureInput": false
						},
						"userProperties": [],
						"typeProperties": {
							"dataflow": {
								"referenceName": "mapping_dataflow",
								"type": "DataFlowReference",
								"parameters": {},
								"datasetParameters": {
									"source1": {
										"fileName": {
											"value": "@pipeline().parameters.FileName1",
											"type": "Expression"
										},
										"folderp": {
											"value": "@pipeline().parameters.folderpath",
											"type": "Expression"
										}
									},
									"sink1": {},
									"sink2": {}
								}
							},
							"staging": {},
							"compute": {
								"coreCount": 8,
								"computeType": "General"
							},
							"traceLevel": "Fine"
						}
					},
					{
						"name": "Set variable1",
						"type": "SetVariable",
						"state": "Inactive",
						"onInactiveMarkAs": "Succeeded",
						"dependsOn": [],
						"policy": {
							"secureOutput": false,
							"secureInput": false
						},
						"userProperties": [],
						"typeProperties": {
							"variableName": "xyz",
							"value": {
								"value": "@pipeline().parameters.folderpath",
								"type": "Expression"
							}
						}
					}
				],
				"policy": {
					"elapsedTimeMetric": {}
				},
				"parameters": {
					"FileName1": {
						"type": "string"
					},
					"folderpath": {
						"type": "string"
					}
				},
				"variables": {
					"abcd": {
						"type": "String"
					},
					"xyz": {
						"type": "String"
					}
				},
				"annotations": []
			},
			"dependsOn": [
				"[concat(variables('factoryId'), '/dataflows/mapping_dataflow')]"
			]
		},
		{
			"name": "[concat(parameters('factoryName'), '/PL_SlowDataChange_type1')]",
			"type": "Microsoft.DataFactory/factories/pipelines",
			"apiVersion": "2018-06-01",
			"properties": {
				"activities": [
					{
						"name": "Data flow1",
						"type": "ExecuteDataFlow",
						"dependsOn": [],
						"policy": {
							"timeout": "0.12:00:00",
							"retry": 0,
							"retryIntervalInSeconds": 30,
							"secureOutput": false,
							"secureInput": false
						},
						"userProperties": [],
						"typeProperties": {
							"dataflow": {
								"referenceName": "dataflow_SDC_Type1",
								"type": "DataFlowReference",
								"parameters": {},
								"datasetParameters": {
									"source1": {},
									"sink1": {}
								}
							},
							"staging": {},
							"compute": {
								"coreCount": 8,
								"computeType": "General"
							},
							"traceLevel": "Fine"
						}
					}
				],
				"policy": {
					"elapsedTimeMetric": {}
				},
				"annotations": []
			},
			"dependsOn": []
		},
		{
			"name": "[concat(parameters('factoryName'), '/PL_slowDC_type2')]",
			"type": "Microsoft.DataFactory/factories/pipelines",
			"apiVersion": "2018-06-01",
			"properties": {
				"activities": [
					{
						"name": "Data flow1",
						"type": "ExecuteDataFlow",
						"dependsOn": [],
						"policy": {
							"timeout": "0.12:00:00",
							"retry": 0,
							"retryIntervalInSeconds": 30,
							"secureOutput": false,
							"secureInput": false
						},
						"userProperties": [],
						"typeProperties": {
							"dataflow": {
								"referenceName": "SDCType2",
								"type": "DataFlowReference",
								"parameters": {},
								"datasetParameters": {
									"source1": {},
									"source2": {},
									"sink1": {},
									"sink2": {}
								}
							},
							"staging": {},
							"compute": {
								"coreCount": 8,
								"computeType": "General"
							},
							"traceLevel": "Fine"
						}
					}
				],
				"policy": {
					"elapsedTimeMetric": {}
				},
				"annotations": []
			},
			"dependsOn": []
		},
		{
			"name": "[concat(parameters('factoryName'), '/incrementalLoadOnOverridedFile')]",
			"type": "Microsoft.DataFactory/factories/pipelines",
			"apiVersion": "2018-06-01",
			"properties": {
				"activities": [
					{
						"name": "Lookup1",
						"type": "Lookup",
						"dependsOn": [],
						"policy": {
							"timeout": "0.12:00:00",
							"retry": 0,
							"retryIntervalInSeconds": 30,
							"secureOutput": false,
							"secureInput": false
						},
						"userProperties": [],
						"typeProperties": {
							"source": {
								"type": "AzureSqlSource",
								"queryTimeout": "02:00:00",
								"partitionOption": "None"
							},
							"dataset": {
								"referenceName": "AzureSqlTable1",
								"type": "DatasetReference",
								"parameters": {}
							}
						}
					},
					{
						"name": "Set variable1",
						"type": "SetVariable",
						"dependsOn": [
							{
								"activity": "Lookup1",
								"dependencyConditions": [
									"Succeeded"
								]
							}
						],
						"policy": {
							"secureOutput": false,
							"secureInput": false
						},
						"userProperties": [],
						"typeProperties": {
							"variableName": "pmaxval",
							"value": {
								"value": "@activity('Lookup1').output.firstRow.Last_Max_CustomerID",
								"type": "Expression"
							}
						}
					},
					{
						"name": "Data flow1",
						"type": "ExecuteDataFlow",
						"dependsOn": [
							{
								"activity": "Set variable1",
								"dependencyConditions": [
									"Succeeded"
								]
							}
						],
						"policy": {
							"timeout": "0.12:00:00",
							"retry": 0,
							"retryIntervalInSeconds": 30,
							"secureOutput": false,
							"secureInput": false
						},
						"userProperties": [],
						"typeProperties": {
							"dataflow": {
								"referenceName": "dataflow2",
								"type": "DataFlowReference",
								"parameters": {
									"parameter123": {
										"value": "@variables('pmaxval')",
										"type": "Expression"
									}
								},
								"datasetParameters": {
									"source1": {},
									"sink1": {}
								}
							},
							"staging": {},
							"compute": {
								"coreCount": 8,
								"computeType": "General"
							},
							"traceLevel": "Fine"
						}
					},
					{
						"name": "Stored procedure1",
						"type": "SqlServerStoredProcedure",
						"dependsOn": [
							{
								"activity": "Data flow1",
								"dependencyConditions": [
									"Succeeded"
								]
							}
						],
						"policy": {
							"timeout": "0.12:00:00",
							"retry": 0,
							"retryIntervalInSeconds": 30,
							"secureOutput": false,
							"secureInput": false
						},
						"userProperties": [],
						"typeProperties": {
							"storedProcedureName": "[[dbo].[updateMetadata]"
						},
						"linkedServiceName": {
							"referenceName": "AzureSqlDatabase1",
							"type": "LinkedServiceReference"
						}
					}
				],
				"policy": {
					"elapsedTimeMetric": {}
				},
				"variables": {
					"pmaxval": {
						"type": "Integer"
					}
				},
				"annotations": [],
				"lastPublishTime": "2025-11-24T13:48:51Z"
			},
			"dependsOn": []
		},
		{
			"name": "[concat(parameters('factoryName'), '/pipeline1')]",
			"type": "Microsoft.DataFactory/factories/pipelines",
			"apiVersion": "2018-06-01",
			"properties": {
				"activities": [
					{
						"name": "Data flow1",
						"type": "ExecuteDataFlow",
						"dependsOn": [],
						"policy": {
							"timeout": "0.12:00:00",
							"retry": 0,
							"retryIntervalInSeconds": 30,
							"secureOutput": false,
							"secureInput": false
						},
						"userProperties": [],
						"typeProperties": {
							"dataflow": {
								"referenceName": "dataflowerrorrows",
								"type": "DataFlowReference",
								"parameters": {},
								"datasetParameters": {
									"source1": {},
									"sink1": {},
									"sink2": {}
								}
							},
							"staging": {},
							"compute": {
								"coreCount": 8,
								"computeType": "General"
							},
							"traceLevel": "None",
							"cacheSinks": {
								"firstRowOnly": true
							}
						}
					}
				],
				"policy": {
					"elapsedTimeMetric": {}
				},
				"annotations": []
			},
			"dependsOn": []
		},
		{
			"name": "[concat(parameters('factoryName'), '/incrementalStorageTrigger')]",
			"type": "Microsoft.DataFactory/factories/triggers",
			"apiVersion": "2018-06-01",
			"properties": {
				"annotations": [],
				"runtimeState": "Stopped",
				"pipelines": [
					{
						"pipelineReference": {
							"referenceName": "incrementalDataLoadDifferentFiles",
							"type": "PipelineReference"
						},
						"parameters": {
							"pfolder": "[parameters('incrementalStorageTrigger_properties_incrementalDataLoadDifferentFiles_parameters_pfolder')]",
							"pfile": "[parameters('incrementalStorageTrigger_properties_incrementalDataLoadDifferentFiles_parameters_pfile')]",
							"puploadedTime": "[parameters('incrementalStorageTrigger_properties_incrementalDataLoadDifferentFiles_parameters_puploadedTime')]"
						}
					}
				],
				"type": "BlobEventsTrigger",
				"typeProperties": {
					"blobPathBeginsWith": "/input/blobs/sales/",
					"blobPathEndsWith": ".csv",
					"ignoreEmptyBlobs": true,
					"scope": "[parameters('incrementalStorageTrigger_properties_typeProperties_scope')]",
					"events": [
						"Microsoft.Storage.BlobCreated"
					]
				}
			},
			"dependsOn": []
		},
		{
			"name": "[concat(parameters('factoryName'), '/NewFileArrivalTrigger')]",
			"type": "Microsoft.DataFactory/factories/triggers",
			"apiVersion": "2018-06-01",
			"properties": {
				"annotations": [],
				"runtimeState": "Stopped",
				"pipelines": [
					{
						"pipelineReference": {
							"referenceName": "PL_MappingDataFlow",
							"type": "PipelineReference"
						},
						"parameters": {
							"FileName1": "[parameters('NewFileArrivalTrigger_properties_PL_MappingDataFlow_parameters_FileName1')]",
							"folderpath": "[parameters('NewFileArrivalTrigger_properties_PL_MappingDataFlow_parameters_folderpath')]"
						}
					}
				],
				"type": "BlobEventsTrigger",
				"typeProperties": {
					"blobPathBeginsWith": "/raw/blobs/",
					"blobPathEndsWith": ".csv",
					"ignoreEmptyBlobs": true,
					"scope": "[parameters('NewFileArrivalTrigger_properties_typeProperties_scope')]",
					"events": [
						"Microsoft.Storage.BlobCreated"
					]
				}
			},
			"dependsOn": [
				"[concat(variables('factoryId'), '/pipelines/PL_MappingDataFlow')]"
			]
		}
	]
}